lllqos/__init__.py
lllqos/py.typed
lllqos-1.0.0.dist-info/METADATA
lllqos-1.0.0.dist-info/WHEEL
lllqos-1.0.0.dist-info/licenses/LICENSE
lllqos-1.0.0.dist-info/RECORD
