Metadata-Version: 2.3
Name: lllqos
Version: 1.0.0
Summary: Linux PM QoS userspace interface
Project-URL: Homepage, https://github.com/brandenburg/py-linux-low-latency-qos
Project-URL: Issues, https://github.com/brandenburg/py-linux-low-latency-qos/issues
Author-email: Björn Brandenburg <bbb@mpi-sws.org>
License-File: LICENSE
Classifier: License :: OSI Approved :: MIT License
Classifier: Operating System :: POSIX :: Linux
Classifier: Programming Language :: Python :: 3
Requires-Python: >=3.7
